netcrackr/__init__.py
netcrackr/main.py
netcrackr-1.0.6.dist-info/METADATA
netcrackr-1.0.6.dist-info/WHEEL
netcrackr-1.0.6.dist-info/entry_points.txt
netcrackr-1.0.6.dist-info/top_level.txt
netcrackr-1.0.6.dist-info/RECORD
