Metadata-Version: 2.4
Name: netcrackr
Version: 1.0.6
Requires-Dist: rich
Requires-Dist: speedtest-cli
Dynamic: requires-dist
